mo_gymnasium/__init__.py
mo_gymnasium/py.typed
mo_gymnasium/utils.py
mo_gymnasium/envs/__init__.py
mo_gymnasium/envs/breakable_bottles/__init__.py
mo_gymnasium/envs/breakable_bottles/breakable_bottles.py
mo_gymnasium/envs/breakable_bottles/assets/Minecraft.ttf
mo_gymnasium/envs/breakable_bottles/assets/bottle.png
mo_gymnasium/envs/breakable_bottles/assets/elf_left.png
mo_gymnasium/envs/breakable_bottles/assets/elf_right.png
mo_gymnasium/envs/breakable_bottles/assets/home.png
mo_gymnasium/envs/breakable_bottles/assets/mountain_bg1.png
mo_gymnasium/envs/breakable_bottles/assets/mountain_bg2.png
mo_gymnasium/envs/continuous_mountain_car/__init__.py
mo_gymnasium/envs/continuous_mountain_car/continuous_mountain_car.py
mo_gymnasium/envs/deep_sea_treasure/__init__.py
mo_gymnasium/envs/deep_sea_treasure/deep_sea_treasure.py
mo_gymnasium/envs/deep_sea_treasure/assets/Minecraft.ttf
mo_gymnasium/envs/deep_sea_treasure/assets/rock.png
mo_gymnasium/envs/deep_sea_treasure/assets/sea_bg.png
mo_gymnasium/envs/deep_sea_treasure/assets/submarine.png
mo_gymnasium/envs/deep_sea_treasure/assets/treasure.png
mo_gymnasium/envs/fishwood/__init__.py
mo_gymnasium/envs/fishwood/fishwood.py
mo_gymnasium/envs/fishwood/assets/Kawa.jpg
mo_gymnasium/envs/fishwood/assets/Mori.jpg
mo_gymnasium/envs/four_room/__init__.py
mo_gymnasium/envs/four_room/four_room.py
mo_gymnasium/envs/fruit_tree/__init__.py
mo_gymnasium/envs/fruit_tree/fruit_tree.py
mo_gymnasium/envs/fruit_tree/assets/agent.png
mo_gymnasium/envs/fruit_tree/assets/node_blue.png
mo_gymnasium/envs/highway/__init__.py
mo_gymnasium/envs/highway/highway.py
mo_gymnasium/envs/lunar_lander/__init__.py
mo_gymnasium/envs/lunar_lander/lunar_lander.py
mo_gymnasium/envs/mario/__init__.py
mo_gymnasium/envs/mario/joypad_space.py
mo_gymnasium/envs/mario/mario.py
mo_gymnasium/envs/minecart/__init__.py
mo_gymnasium/envs/minecart/mine_config.json
mo_gymnasium/envs/minecart/mine_config_det.json
mo_gymnasium/envs/minecart/minecart.py
mo_gymnasium-1.3.1.dist-info/LICENSE
mo_gymnasium-1.3.1.dist-info/METADATA
mo_gymnasium-1.3.1.dist-info/WHEEL
mo_gymnasium-1.3.1.dist-info/top_level.txt
mo_gymnasium-1.3.1.dist-info/RECORD
