Metadata-Version: 2.1
Name: mo-gymnasium
Version: 1.3.1
Summary: A standard API for MORL and a diverse set of reference environments.
Author-email: Farama Foundation <contact@farama.org>
License: MIT License
Project-URL: Homepage, https://mo-gymnasium.farama.org
Project-URL: Repository, https://github.com/Farama-Foundation/MO-Gymnasium
Project-URL: Documentation, https://mo-gymnasium.farama.org
Project-URL: Bug Report, https://github.com/Farama-Foundation/MO-Gymnasium/issues
Keywords: Reinforcement Learning,Multi-Objective,RL,AI,Gymnasium
Classifier: Development Status :: 4 - Beta
Classifier: License :: OSI Approved :: MIT License
Classifier: Programming Language :: Python :: 3
Classifier: Programming Language :: Python :: 3.8
Classifier: Programming Language :: Python :: 3.9
Classifier: Programming Language :: Python :: 3.10
Classifier: Programming Language :: Python :: 3.11
Classifier: Programming Language :: Python :: 3.12
Classifier: Intended Audience :: Science/Research
Classifier: Topic :: Scientific/Engineering :: Artificial Intelligence
Requires-Python: >=3.8
License-File: LICENSE
Requires-Dist: gymnasium >=1.0.0
Requires-Dist: numpy <2.0,>=1.21.0
Requires-Dist: pygame >=2.1.3
Requires-Dist: scipy >=1.7.3
Provides-Extra: all
Requires-Dist: nes-py ; extra == 'all'
Requires-Dist: gym-super-mario-bros ; extra == 'all'
Requires-Dist: scipy >=1.7.3 ; extra == 'all'
Requires-Dist: imageio >=2.14.1 ; extra == 'all'
Requires-Dist: mujoco >=2.2.0 ; extra == 'all'
Requires-Dist: highway-env >=1.9.1 ; extra == 'all'
Requires-Dist: box2d-py ==2.3.5 ; extra == 'all'
Requires-Dist: pygame >=2.1.3 ; extra == 'all'
Requires-Dist: swig ==4.* ; extra == 'all'
Provides-Extra: box2d
Requires-Dist: box2d-py ==2.3.5 ; extra == 'box2d'
Requires-Dist: pygame >=2.1.3 ; extra == 'box2d'
Requires-Dist: swig ==4.* ; extra == 'box2d'
Provides-Extra: highway
Requires-Dist: highway-env >=1.8 ; extra == 'highway'
Provides-Extra: mario
Requires-Dist: nes-py ; extra == 'mario'
Requires-Dist: gym-super-mario-bros ; extra == 'mario'
Provides-Extra: minecart
Requires-Dist: scipy >=1.7.3 ; extra == 'minecart'
Provides-Extra: mujoco
Requires-Dist: mujoco >=2.2.0 ; extra == 'mujoco'
Requires-Dist: imageio >=2.14.1 ; extra == 'mujoco'
Provides-Extra: testing
Requires-Dist: pytest ==7.1.3 ; extra == 'testing'
